test/__init__.py
test/main.py
burphttprequest-0.1.0.dist-info/LICENSE
burphttprequest-0.1.0.dist-info/METADATA
burphttprequest-0.1.0.dist-info/WHEEL
burphttprequest-0.1.0.dist-info/top_level.txt
burphttprequest-0.1.0.dist-info/RECORD
