Metadata-Version: 2.2
Name: burphttprequest
Version: 0.1.0
Summary: 一个用于解析和发送HTTP请求的Python库，支持代理和保存响应
Home-page: https://github.com/kasus/burphttprequest
Author: kasus
Author-email: 
Classifier: Programming Language :: Python :: 3
Classifier: License :: OSI Approved :: MIT License
Classifier: Operating System :: OS Independent
Requires-Python: >=3.6
License-File: LICENSE
Requires-Dist: requests>=2.25.0
Dynamic: author
Dynamic: classifier
Dynamic: description
Dynamic: description-content-type
Dynamic: home-page
Dynamic: requires-dist
Dynamic: requires-python
Dynamic: summary
